raidionicsval/__init__.py
raidionicsval/__main__.py
raidionicsval/compute.py
raidionicsval/Computation/__init__.py
raidionicsval/Computation/dice_computation.py
raidionicsval/Computation/dice_computation_instance.py
raidionicsval/Computation/medpy_metrics.py
raidionicsval/Computation/standalone_computation.py
raidionicsval/Plotting/__init__.py
raidionicsval/Plotting/agreement_plot.py
raidionicsval/Plotting/classification_plot.py
raidionicsval/Plotting/confidence_intervals_plot.py
raidionicsval/Plotting/metric_versus_binned_boxplot.py
raidionicsval/Studies/AbstractStudy.py
raidionicsval/Studies/ClassificationStudy.py
raidionicsval/Studies/SegmentationStudy.py
raidionicsval/Studies/__init__.py
raidionicsval/Studies/study_connector.py
raidionicsval/Utils/PatientMetricsStructure.py
raidionicsval/Utils/__init__.py
raidionicsval/Utils/io_converters.py
raidionicsval/Utils/latex_converter.py
raidionicsval/Utils/resources.py
raidionicsval/Validation/__init__.py
raidionicsval/Validation/extra_metrics_computation.py
raidionicsval/Validation/instance_segmentation_validation.py
raidionicsval/Validation/kfold_model_validation.py
raidionicsval/Validation/kfold_model_validation_classification.py
raidionicsval/Validation/validation_utilities.py
raidionicsval/Validation/validation_utilities_classification.py
raidionicsval-1.1.1.dist-info/licenses/LICENSE.md
tests/__init__.py
tests/conftest.py
tests/download_resources.py
raidionicsval-1.1.1.dist-info/METADATA
raidionicsval-1.1.1.dist-info/WHEEL
raidionicsval-1.1.1.dist-info/entry_points.txt
raidionicsval-1.1.1.dist-info/top_level.txt
raidionicsval-1.1.1.dist-info/RECORD
