Metadata-Version: 2.4
Name: raidionicsval
Version: 1.1.1
Summary: Raidionics backend for running validation and metrics computation
Author-email: David Bouget <david.bouget@sintef.no>
License: BSD-2-Clause
Requires-Python: >=3.9
License-File: LICENSE.md
Requires-Dist: arch
Requires-Dist: h5py
Requires-Dist: nibabel
Requires-Dist: pandas
Requires-Dist: SimpleITK<=2.4.1
Requires-Dist: statsmodels
Requires-Dist: scikit-image
Requires-Dist: tqdm
Requires-Dist: scikit-learn
Requires-Dist: seaborn
Requires-Dist: Jinja2
Dynamic: license-file
